m3Drop/ControlDeviceCPU.py
m3Drop/ControlDeviceGPU.py
m3Drop/CoreCPU.py
m3Drop/CoreGPU.py
m3Drop/DiagnosticsCPU.py
m3Drop/DiagnosticsGPU.py
m3Drop/NormalizationCPU.py
m3Drop/NormalizationGPU.py
m3Drop/__init__.py
m3drop-0.4.55.dist-info/licenses/LICENSE
m3drop-0.4.55.dist-info/METADATA
m3drop-0.4.55.dist-info/WHEEL
m3drop-0.4.55.dist-info/top_level.txt
m3drop-0.4.55.dist-info/RECORD
