Metadata-Version: 2.4
Name: M3Drop
Version: 0.4.55
Summary: A Python implementation of the M3Drop single-cell RNA-seq analysis tool.
Home-page: https://github.com/PragalvhaSharma/m3DropNew
Author: Tallulah Andrews
Author-email: tandrew6@uwo.ca
License: MIT
Classifier: Programming Language :: Python :: 3
Classifier: Operating System :: OS Independent
Classifier: License :: OSI Approved :: MIT License
Classifier: Intended Audience :: Science/Research
Classifier: Topic :: Scientific/Engineering :: Bio-Informatics
Requires-Python: >=3.8
License-File: LICENSE
Requires-Dist: anndata>=0.8.0
Requires-Dist: h5py>=3.8.0
Requires-Dist: matplotlib>=3.5.0
Requires-Dist: matplotlib-venn>=0.11
Requires-Dist: memory_profiler>=0.60.0
Requires-Dist: numpy>=1.21.0
Requires-Dist: pandas>=1.5.0
Requires-Dist: scanpy>=1.9.0
Requires-Dist: scikit-learn>=1.0.0
Requires-Dist: scipy>=1.8.0
Requires-Dist: seaborn>=0.11.0
Requires-Dist: statsmodels>=0.13.0
Requires-Dist: numba>=0.57.0
Requires-Dist: psutil>=5.9.0
Requires-Dist: py-cpuinfo
Provides-Extra: gpu
Requires-Dist: cupy-cuda12x; extra == "gpu"
Dynamic: author
Dynamic: author-email
Dynamic: classifier
Dynamic: description
Dynamic: description-content-type
Dynamic: home-page
Dynamic: license
Dynamic: license-file
Dynamic: provides-extra
Dynamic: requires-dist
Dynamic: requires-python
Dynamic: summary
